realdistance_mandrin35/__init__.py
realdistance_mandrin35-0.0.1.dist-info/METADATA
realdistance_mandrin35-0.0.1.dist-info/WHEEL
realdistance_mandrin35-0.0.1.dist-info/top_level.txt
realdistance_mandrin35-0.0.1.dist-info/RECORD
